{
  "name" : "City",
  "preName" : "",
  "comment" : null,
  "templateGroupName" : "Default",
  "fullColumn" : [ {
    "name" : "id",
    "comment" : null,
    "type" : null,
    "shortType" : null,
    "custom" : false,
    "ext" : { }
  }, {
    "name" : "cityCode",
    "comment" : null,
    "type" : null,
    "shortType" : null,
    "custom" : false,
    "ext" : { }
  }, {
    "name" : "cityName",
    "comment" : null,
    "type" : null,
    "shortType" : null,
    "custom" : false,
    "ext" : { }
  }, {
    "name" : "remark",
    "comment" : null,
    "type" : null,
    "shortType" : null,
    "custom" : false,
    "ext" : { }
  } ],
  "pkColumn" : null,
  "otherColumn" : null,
  "savePackageName" : "com.arbitrary.test.city",
  "savePath" : "./src/main/java/com/arbitrary/test/city",
  "saveModelName" : "springboot"
}